Metadata-Version: 1.0
Name: udacity-distr
Version: 0.5
Summary: Gaussian and Binomial distributions
Home-page: UNKNOWN
Author: saber_bounehas
Author-email: samirsamado5@gmail.com
License: UNKNOWN
Platform: UNKNOWN
